Workbook

Sheet Orders
A1: 💰 COMBINED SALES TRACKER — BOTH FRONTS
A2: Order ID | B2: Date | C2: Front | D2: Drop ID | E2: Etsy Listing ID | F2: Product Title | G2: Niche / Design | H2: Sale Price ($) | I2: Shipping Charged | J2: Printify Cost ($) | K2: Printify Ship ($) | L2: Etsy Txn Fee | M2: Etsy Payment Fee | N2: Etsy Listing Fee | O2: Etsy Ads Spend | P2: Total Costs ($) | Q2: Net Profit ($) | R2: Margin % | S2: UTM Source | T2: Notes
A3: ORD-0001 | B3: 2026-03-05 | C3: A | D3: DROP-01 | F3: Rotation Ready Shirt | Sneakerhead Tee | G3: Sneaker Culture | H3: 54.99 | I3: 0 | J3: 14.5 | K3: 5 | L3: =H3*0.065 | M3: =H3*0.03+0.25 | N3: 0.2 | O3: 0 | P3: =J3+K3+L3+M3+N3+O3 | Q3: =H3+I3-P3 | R3: =IF((H3+I3)>0,Q3/(H3+I3),0) | S3: sneakerapp/community_tab

Sheet Monthly P&L
A1: 📅 MONTHLY P&L — BY FRONT
A2: FRONT A — SNEAKER CULTURE
A3: Month | B3: Orders | C3: Gross Revenue | D3: Costs | E3: Net Profit | F3: Margin% | G3: Avg Order | H3: Best Design | I3: Drop ID
A4: Jan 2026 | B4: =SUMPRODUCT((MONTH(Orders!B$3:B$3000)=1)*(YEAR(Orders!B$3:B$3000)=2026)*(Orders!C$3:C$3000="A")) | C4: =SUMPRODUCT((MONTH(Orders!B$3:B$3000)=1)*(YEAR(Orders!B$3:B$3000)=2026)*(Orders!C$3:C$3000="A")*Orders!H$3:H$3000) | D4: =SUMPRODUCT((MONTH(Orders!B$3:B$3000)=1)*(YEAR(Orders!B$3:B$3000)=2026)*(Orders!C$3:C$3000="A")*Orders!P$3:P$3000) | E4: =C4-D4 | F4: =IF(C4>0,E4/C4,0) | G4: =IF(B4>0,C4/B4,0)
A5: Feb 2026 | B5: =SUMPRODUCT((MONTH(Orders!B$3:B$3000)=2)*(YEAR(Orders!B$3:B$3000)=2026)*(Orders!C$3:C$3000="A")) | C5: =SUMPRODUCT((MONTH(Orders!B$3:B$3000)=2)*(YEAR(Orders!B$3:B$3000)=2026)*(Orders!C$3:C$3000="A")*Orders!H$3:H$3000) | D5: =SUMPRODUCT((MONTH(Orders!B$3:B$3000)=2)*(YEAR(Orders!B$3:B$3000)=2026)*(Orders!C$3:C$3000="A")*Orders!P$3:P$3000) | E5: =C5-D5 | F5: =IF(C5>0,E5/C5,0) | G5: =IF(B5>0,C5/B5,0)
A6: Mar 2026 | B6: =SUMPRODUCT((MONTH(Orders!B$3:B$3000)=3)*(YEAR(Orders!B$3:B$3000)=2026)*(Orders!C$3:C$3000="A")) | C6: =SUMPRODUCT((MONTH(Orders!B$3:B$3000)=3)*(YEAR(Orders!B$3:B$3000)=2026)*(Orders!C$3:C$3000="A")*Orders!H$3:H$3000) | D6: =SUMPRODUCT((MONTH(Orders!B$3:B$3000)=3)*(YEAR(Orders!B$3:B$3000)=2026)*(Orders!C$3:C$3000="A")*Orders!P$3:P$3000) | E6: =C6-D6 | F6: =IF(C6>0,E6/C6,0) | G6: =IF(B6>0,C6/B6,0)
A7: Apr 2026 | B7: =SUMPRODUCT((MONTH(Orders!B$3:B$3000)=4)*(YEAR(Orders!B$3:B$3000)=2026)*(Orders!C$3:C$3000="A")) | C7: =SUMPRODUCT((MONTH(Orders!B$3:B$3000)=4)*(YEAR(Orders!B$3:B$3000)=2026)*(Orders!C$3:C$3000="A")*Orders!H$3:H$3000) | D7: =SUMPRODUCT((MONTH(Orders!B$3:B$3000)=4)*(YEAR(Orders!B$3:B$3000)=2026)*(Orders!C$3:C$3000="A")*Orders!P$3:P$3000) | E7: =C7-D7 | F7: =IF(C7>0,E7/C7,0) | G7: =IF(B7>0,C7/B7,0)
A8: May 2026 | B8: =SUMPRODUCT((MONTH(Orders!B$3:B$3000)=5)*(YEAR(Orders!B$3:B$3000)=2026)*(Orders!C$3:C$3000="A")) | C8: =SUMPRODUCT((MONTH(Orders!B$3:B$3000)=5)*(YEAR(Orders!B$3:B$3000)=2026)*(Orders!C$3:C$3000="A")*Orders!H$3:H$3000) | D8: =SUMPRODUCT((MONTH(Orders!B$3:B$3000)=5)*(YEAR(Orders!B$3:B$3000)=2026)*(Orders!C$3:C$3000="A")*Orders!P$3:P$3000) | E8: =C8-D8 | F8: =IF(C8>0,E8/C8,0) | G8: =IF(B8>0,C8/B8,0)
A9: Jun 2026 | B9: =SUMPRODUCT((MONTH(Orders!B$3:B$3000)=6)*(YEAR(Orders!B$3:B$3000)=2026)*(Orders!C$3:C$3000="A")) | C9: =SUMPRODUCT((MONTH(Orders!B$3:B$3000)=6)*(YEAR(Orders!B$3:B$3000)=2026)*(Orders!C$3:C$3000="A")*Orders!H$3:H$3000) | D9: =SUMPRODUCT((MONTH(Orders!B$3:B$3000)=6)*(YEAR(Orders!B$3:B$3000)=2026)*(Orders!C$3:C$3000="A")*Orders!P$3:P$3000) | E9: =C9-D9 | F9: =IF(C9>0,E9/C9,0) | G9: =IF(B9>0,C9/B9,0)
A10: Jul 2026 | B10: =SUMPRODUCT((MONTH(Orders!B$3:B$3000)=7)*(YEAR(Orders!B$3:B$3000)=2026)*(Orders!C$3:C$3000="A")) | C10: =SUMPRODUCT((MONTH(Orders!B$3:B$3000)=7)*(YEAR(Orders!B$3:B$3000)=2026)*(Orders!C$3:C$3000="A")*Orders!H$3:H$3000) | D10: =SUMPRODUCT((MONTH(Orders!B$3:B$3000)=7)*(YEAR(Orders!B$3:B$3000)=2026)*(Orders!C$3:C$3000="A")*Orders!P$3:P$3000) | E10: =C10-D10 | F10: =IF(C10>0,E10/C10,0) | G10: =IF(B10>0,C10/B10,0)
A11: Aug 2026 | B11: =SUMPRODUCT((MONTH(Orders!B$3:B$3000)=8)*(YEAR(Orders!B$3:B$3000)=2026)*(Orders!C$3:C$3000="A")) | C11: =SUMPRODUCT((MONTH(Orders!B$3:B$3000)=8)*(YEAR(Orders!B$3:B$3000)=2026)*(Orders!C$3:C$3000="A")*Orders!H$3:H$3000) | D11: =SUMPRODUCT((MONTH(Orders!B$3:B$3000)=8)*(YEAR(Orders!B$3:B$3000)=2026)*(Orders!C$3:C$3000="A")*Orders!P$3:P$3000) | E11: =C11-D11 | F11: =IF(C11>0,E11/C11,0) | G11: =IF(B11>0,C11/B11,0)
A12: Sep 2026 | B12: =SUMPRODUCT((MONTH(Orders!B$3:B$3000)=9)*(YEAR(Orders!B$3:B$3000)=2026)*(Orders!C$3:C$3000="A")) | C12: =SUMPRODUCT((MONTH(Orders!B$3:B$3000)=9)*(YEAR(Orders!B$3:B$3000)=2026)*(Orders!C$3:C$3000="A")*Orders!H$3:H$3000) | D12: =SUMPRODUCT((MONTH(Orders!B$3:B$3000)=9)*(YEAR(Orders!B$3:B$3000)=2026)*(Orders!C$3:C$3000="A")*Orders!P$3:P$3000) | E12: =C12-D12 | F12: =IF(C12>0,E12/C12,0) | G12: =IF(B12>0,C12/B12,0)
A13: Oct 2026 | B13: =SUMPRODUCT((MONTH(Orders!B$3:B$3000)=10)*(YEAR(Orders!B$3:B$3000)=2026)*(Orders!C$3:C$3000="A")) | C13: =SUMPRODUCT((MONTH(Orders!B$3:B$3000)=10)*(YEAR(Orders!B$3:B$3000)=2026)*(Orders!C$3:C$3000="A")*Orders!H$3:H$3000) | D13: =SUMPRODUCT((MONTH(Orders!B$3:B$3000)=10)*(YEAR(Orders!B$3:B$3000)=2026)*(Orders!C$3:C$3000="A")*Orders!P$3:P$3000) | E13: =C13-D13 | F13: =IF(C13>0,E13/C13,0) | G13: =IF(B13>0,C13/B13,0)
A14: Nov 2026 | B14: =SUMPRODUCT((MONTH(Orders!B$3:B$3000)=11)*(YEAR(Orders!B$3:B$3000)=2026)*(Orders!C$3:C$3000="A")) | C14: =SUMPRODUCT((MONTH(Orders!B$3:B$3000)=11)*(YEAR(Orders!B$3:B$3000)=2026)*(Orders!C$3:C$3000="A")*Orders!H$3:H$3000) | D14: =SUMPRODUCT((MONTH(Orders!B$3:B$3000)=11)*(YEAR(Orders!B$3:B$3000)=2026)*(Orders!C$3:C$3000="A")*Orders!P$3:P$3000) | E14: =C14-D14 | F14: =IF(C14>0,E14/C14,0) | G14: =IF(B14>0,C14/B14,0)
A15: Dec 2026 | B15: =SUMPRODUCT((MONTH(Orders!B$3:B$3000)=12)*(YEAR(Orders!B$3:B$3000)=2026)*(Orders!C$3:C$3000="A")) | C15: =SUMPRODUCT((MONTH(Orders!B$3:B$3000)=12)*(YEAR(Orders!B$3:B$3000)=2026)*(Orders!C$3:C$3000="A")*Orders!H$3:H$3000) | D15: =SUMPRODUCT((MONTH(Orders!B$3:B$3000)=12)*(YEAR(Orders!B$3:B$3000)=2026)*(Orders!C$3:C$3000="A")*Orders!P$3:P$3000) | E15: =C15-D15 | F15: =IF(C15>0,E15/C15,0) | G15: =IF(B15>0,C15/B15,0)
A18: FRONT B — GENERALIZED DESIGNS
A19: Month | B19: Orders | C19: Gross Revenue | D19: Costs | E19: Net Profit | F19: Margin% | G19: Avg Order | H19: Best Design | I19: Drop ID
A20: Jan 2026 | B20: =SUMPRODUCT((MONTH(Orders!B$3:B$3000)=1)*(YEAR(Orders!B$3:B$3000)=2026)*(Orders!C$3:C$3000="B")) | C20: =SUMPRODUCT((MONTH(Orders!B$3:B$3000)=1)*(YEAR(Orders!B$3:B$3000)=2026)*(Orders!C$3:C$3000="B")*Orders!H$3:H$3000) | D20: =SUMPRODUCT((MONTH(Orders!B$3:B$3000)=1)*(YEAR(Orders!B$3:B$3000)=2026)*(Orders!C$3:C$3000="B")*Orders!P$3:P$3000) | E20: =C20-D20 | F20: =IF(C20>0,E20/C20,0) | G20: =IF(B20>0,C20/B20,0)
A21: Feb 2026 | B21: =SUMPRODUCT((MONTH(Orders!B$3:B$3000)=2)*(YEAR(Orders!B$3:B$3000)=2026)*(Orders!C$3:C$3000="B")) | C21: =SUMPRODUCT((MONTH(Orders!B$3:B$3000)=2)*(YEAR(Orders!B$3:B$3000)=2026)*(Orders!C$3:C$3000="B")*Orders!H$3:H$3000) | D21: =SUMPRODUCT((MONTH(Orders!B$3:B$3000)=2)*(YEAR(Orders!B$3:B$3000)=2026)*(Orders!C$3:C$3000="B")*Orders!P$3:P$3000) | E21: =C21-D21 | F21: =IF(C21>0,E21/C21,0) | G21: =IF(B21>0,C21/B21,0)
A22: Mar 2026 | B22: =SUMPRODUCT((MONTH(Orders!B$3:B$3000)=3)*(YEAR(Orders!B$3:B$3000)=2026)*(Orders!C$3:C$3000="B")) | C22: =SUMPRODUCT((MONTH(Orders!B$3:B$3000)=3)*(YEAR(Orders!B$3:B$3000)=2026)*(Orders!C$3:C$3000="B")*Orders!H$3:H$3000) | D22: =SUMPRODUCT((MONTH(Orders!B$3:B$3000)=3)*(YEAR(Orders!B$3:B$3000)=2026)*(Orders!C$3:C$3000="B")*Orders!P$3:P$3000) | E22: =C22-D22 | F22: =IF(C22>0,E22/C22,0) | G22: =IF(B22>0,C22/B22,0)
A23: Apr 2026 | B23: =SUMPRODUCT((MONTH(Orders!B$3:B$3000)=4)*(YEAR(Orders!B$3:B$3000)=2026)*(Orders!C$3:C$3000="B")) | C23: =SUMPRODUCT((MONTH(Orders!B$3:B$3000)=4)*(YEAR(Orders!B$3:B$3000)=2026)*(Orders!C$3:C$3000="B")*Orders!H$3:H$3000) | D23: =SUMPRODUCT((MONTH(Orders!B$3:B$3000)=4)*(YEAR(Orders!B$3:B$3000)=2026)*(Orders!C$3:C$3000="B")*Orders!P$3:P$3000) | E23: =C23-D23 | F23: =IF(C23>0,E23/C23,0) | G23: =IF(B23>0,C23/B23,0)
A24: May 2026 | B24: =SUMPRODUCT((MONTH(Orders!B$3:B$3000)=5)*(YEAR(Orders!B$3:B$3000)=2026)*(Orders!C$3:C$3000="B")) | C24: =SUMPRODUCT((MONTH(Orders!B$3:B$3000)=5)*(YEAR(Orders!B$3:B$3000)=2026)*(Orders!C$3:C$3000="B")*Orders!H$3:H$3000) | D24: =SUMPRODUCT((MONTH(Orders!B$3:B$3000)=5)*(YEAR(Orders!B$3:B$3000)=2026)*(Orders!C$3:C$3000="B")*Orders!P$3:P$3000) | E24: =C24-D24 | F24: =IF(C24>0,E24/C24,0) | G24: =IF(B24>0,C24/B24,0)
A25: Jun 2026 | B25: =SUMPRODUCT((MONTH(Orders!B$3:B$3000)=6)*(YEAR(Orders!B$3:B$3000)=2026)*(Orders!C$3:C$3000="B")) | C25: =SUMPRODUCT((MONTH(Orders!B$3:B$3000)=6)*(YEAR(Orders!B$3:B$3000)=2026)*(Orders!C$3:C$3000="B")*Orders!H$3:H$3000) | D25: =SUMPRODUCT((MONTH(Orders!B$3:B$3000)=6)*(YEAR(Orders!B$3:B$3000)=2026)*(Orders!C$3:C$3000="B")*Orders!P$3:P$3000) | E25: =C25-D25 | F25: =IF(C25>0,E25/C25,0) | G25: =IF(B25>0,C25/B25,0)
A26: Jul 2026 | B26: =SUMPRODUCT((MONTH(Orders!B$3:B$3000)=7)*(YEAR(Orders!B$3:B$3000)=2026)*(Orders!C$3:C$3000="B")) | C26: =SUMPRODUCT((MONTH(Orders!B$3:B$3000)=7)*(YEAR(Orders!B$3:B$3000)=2026)*(Orders!C$3:C$3000="B")*Orders!H$3:H$3000) | D26: =SUMPRODUCT((MONTH(Orders!B$3:B$3000)=7)*(YEAR(Orders!B$3:B$3000)=2026)*(Orders!C$3:C$3000="B")*Orders!P$3:P$3000) | E26: =C26-D26 | F26: =IF(C26>0,E26/C26,0) | G26: =IF(B26>0,C26/B26,0)
A27: Aug 2026 | B27: =SUMPRODUCT((MONTH(Orders!B$3:B$3000)=8)*(YEAR(Orders!B$3:B$3000)=2026)*(Orders!C$3:C$3000="B")) | C27: =SUMPRODUCT((MONTH(Orders!B$3:B$3000)=8)*(YEAR(Orders!B$3:B$3000)=2026)*(Orders!C$3:C$3000="B")*Orders!H$3:H$3000) | D27: =SUMPRODUCT((MONTH(Orders!B$3:B$3000)=8)*(YEAR(Orders!B$3:B$3000)=2026)*(Orders!C$3:C$3000="B")*Orders!P$3:P$3000) | E27: =C27-D27 | F27: =IF(C27>0,E27/C27,0) | G27: =IF(B27>0,C27/B27,0)
A28: Sep 2026 | B28: =SUMPRODUCT((MONTH(Orders!B$3:B$3000)=9)*(YEAR(Orders!B$3:B$3000)=2026)*(Orders!C$3:C$3000="B")) | C28: =SUMPRODUCT((MONTH(Orders!B$3:B$3000)=9)*(YEAR(Orders!B$3:B$3000)=2026)*(Orders!C$3:C$3000="B")*Orders!H$3:H$3000) | D28: =SUMPRODUCT((MONTH(Orders!B$3:B$3000)=9)*(YEAR(Orders!B$3:B$3000)=2026)*(Orders!C$3:C$3000="B")*Orders!P$3:P$3000) | E28: =C28-D28 | F28: =IF(C28>0,E28/C28,0) | G28: =IF(B28>0,C28/B28,0)
A29: Oct 2026 | B29: =SUMPRODUCT((MONTH(Orders!B$3:B$3000)=10)*(YEAR(Orders!B$3:B$3000)=2026)*(Orders!C$3:C$3000="B")) | C29: =SUMPRODUCT((MONTH(Orders!B$3:B$3000)=10)*(YEAR(Orders!B$3:B$3000)=2026)*(Orders!C$3:C$3000="B")*Orders!H$3:H$3000) | D29: =SUMPRODUCT((MONTH(Orders!B$3:B$3000)=10)*(YEAR(Orders!B$3:B$3000)=2026)*(Orders!C$3:C$3000="B")*Orders!P$3:P$3000) | E29: =C29-D29 | F29: =IF(C29>0,E29/C29,0) | G29: =IF(B29>0,C29/B29,0)
A30: Nov 2026 | B30: =SUMPRODUCT((MONTH(Orders!B$3:B$3000)=11)*(YEAR(Orders!B$3:B$3000)=2026)*(Orders!C$3:C$3000="B")) | C30: =SUMPRODUCT((MONTH(Orders!B$3:B$3000)=11)*(YEAR(Orders!B$3:B$3000)=2026)*(Orders!C$3:C$3000="B")*Orders!H$3:H$3000) | D30: =SUMPRODUCT((MONTH(Orders!B$3:B$3000)=11)*(YEAR(Orders!B$3:B$3000)=2026)*(Orders!C$3:C$3000="B")*Orders!P$3:P$3000) | E30: =C30-D30 | F30: =IF(C30>0,E30/C30,0) | G30: =IF(B30>0,C30/B30,0)
A31: Dec 2026 | B31: =SUMPRODUCT((MONTH(Orders!B$3:B$3000)=12)*(YEAR(Orders!B$3:B$3000)=2026)*(Orders!C$3:C$3000="B")) | C31: =SUMPRODUCT((MONTH(Orders!B$3:B$3000)=12)*(YEAR(Orders!B$3:B$3000)=2026)*(Orders!C$3:C$3000="B")*Orders!H$3:H$3000) | D31: =SUMPRODUCT((MONTH(Orders!B$3:B$3000)=12)*(YEAR(Orders!B$3:B$3000)=2026)*(Orders!C$3:C$3000="B")*Orders!P$3:P$3000) | E31: =C31-D31 | F31: =IF(C31>0,E31/C31,0) | G31: =IF(B31>0,C31/B31,0)
